example_wolt_package_debug_ci_issues/__init__.py
example_wolt_package_debug_ci_issues/py.typed
example_wolt_package_debug_ci_issues-0.0.7.dist-info/WHEEL
example_wolt_package_debug_ci_issues-0.0.7.dist-info/METADATA
example_wolt_package_debug_ci_issues-0.0.7.dist-info/RECORD
