Metadata-Version: 2.1
Name: example-wolt-package-debug-ci-issues
Version: 0.0.7
Summary: what it says on the tin, not a real package
Home-page: https://rtaycher.github.io/example_wolt_package_debug_ci_issues
License: MIT
Author: Roman A. Taycher
Author-email: rtaycher.devmail@gmail.com
Requires-Python: >=3.7.1,<4.0
Classifier: Development Status :: 4 - Beta
Classifier: Intended Audience :: Developers
Classifier: License :: OSI Approved :: MIT License
Classifier: Operating System :: OS Independent
Classifier: Programming Language :: Python
Classifier: Programming Language :: Python :: 3
Classifier: Programming Language :: Python :: 3.8
Classifier: Programming Language :: Python :: 3.9
Classifier: Programming Language :: Python :: 3.10
Classifier: Programming Language :: Python :: 3.11
Classifier: Programming Language :: Python :: 3
Classifier: Programming Language :: Python :: 3.7
Classifier: Programming Language :: Python :: 3.8
Classifier: Programming Language :: Python :: 3.9
Classifier: Topic :: Software Development :: Libraries :: Python Modules
Classifier: Typing :: Typed
Project-URL: Documentation, https://rtaycher.github.io/example_wolt_package_debug_ci_issues
Project-URL: Repository, https://github.com/rtaycher/example_wolt_package_debug_ci_issues
